fhzz/__init__.py
fhzz/__main__.py
fhzz/campaign.py
fhzz/main.py
fhzz-0.1.0.dist-info/LICENSE
fhzz-0.1.0.dist-info/METADATA
fhzz-0.1.0.dist-info/WHEEL
fhzz-0.1.0.dist-info/entry_points.txt
fhzz-0.1.0.dist-info/top_level.txt
fhzz-0.1.0.dist-info/RECORD
